{
  "id": "ede8b98b-2b7c-4ec0-9be3-c80d6d50e50b",
  "prevId": "1dde6c0f-a834-4e19-bd2b-30e5fe5d7d61",
  "version": "7",
  "dialect": "postgresql",
  "tables": {
    "public.canvas": {
      "name": "canvas",
      "schema": "",
      "columns": {
        "id": {
          "name": "id",
          "type": "uuid",
          "primaryKey": true,
          "notNull": true,
          "default": "gen_random_uuid()"
        },
        "project_id": {
          "name": "project_id",
          "type": "uuid",
          "primaryKey": false,
          "notNull": true
        },
        "scale": {
          "name": "scale",
          "type": "numeric",
          "primaryKey": false,
          "notNull": false
        },
        "position": {
          "name": "position",
          "type": "jsonb",
          "primaryKey": false,
          "notNull": false
        }
      },
      "indexes": {},
      "foreignKeys": {
        "canvas_project_id_projects_id_fk": {
          "name": "canvas_project_id_projects_id_fk",
          "tableFrom": "canvas",
          "tableTo": "projects",
          "columnsFrom": [
            "project_id"
          ],
          "columnsTo": [
            "id"
          ],
          "onDelete": "no action",
          "onUpdate": "no action"
        }
      },
      "compositePrimaryKeys": {},
      "uniqueConstraints": {},
      "policies": {},
      "checkConstraints": {},
      "isRLSEnabled": true
    },
    "public.frames": {
      "name": "frames",
      "schema": "",
      "columns": {
        "id": {
          "name": "id",
          "type": "uuid",
          "primaryKey": true,
          "notNull": true,
          "default": "gen_random_uuid()"
        },
        "canvas_id": {
          "name": "canvas_id",
          "type": "uuid",
          "primaryKey": false,
          "notNull": true
        },
        "type": {
          "name": "type",
          "type": "frame_type",
          "typeSchema": "public",
          "primaryKey": false,
          "notNull": true
        },
        "x": {
          "name": "x",
          "type": "numeric",
          "primaryKey": false,
          "notNull": true
        },
        "y": {
          "name": "y",
          "type": "numeric",
          "primaryKey": false,
          "notNull": true
        },
        "width": {
          "name": "width",
          "type": "numeric",
          "primaryKey": false,
          "notNull": true
        },
        "height": {
          "name": "height",
          "type": "numeric",
          "primaryKey": false,
          "notNull": true
        },
        "url": {
          "name": "url",
          "type": "varchar",
          "primaryKey": false,
          "notNull": false
        }
      },
      "indexes": {},
      "foreignKeys": {
        "frames_canvas_id_canvas_id_fk": {
          "name": "frames_canvas_id_canvas_id_fk",
          "tableFrom": "frames",
          "tableTo": "canvas",
          "columnsFrom": [
            "canvas_id"
          ],
          "columnsTo": [
            "id"
          ],
          "onDelete": "no action",
          "onUpdate": "no action"
        }
      },
      "compositePrimaryKeys": {},
      "uniqueConstraints": {},
      "policies": {},
      "checkConstraints": {},
      "isRLSEnabled": true
    },
    "public.projects": {
      "name": "projects",
      "schema": "",
      "columns": {
        "id": {
          "name": "id",
          "type": "uuid",
          "primaryKey": true,
          "notNull": true,
          "default": "gen_random_uuid()"
        },
        "name": {
          "name": "name",
          "type": "varchar(255)",
          "primaryKey": false,
          "notNull": false
        },
        "preview_url": {
          "name": "preview_url",
          "type": "varchar(2048)",
          "primaryKey": false,
          "notNull": false
        },
        "created_at": {
          "name": "created_at",
          "type": "timestamp with time zone",
          "primaryKey": false,
          "notNull": false,
          "default": "now()"
        },
        "updated_at": {
          "name": "updated_at",
          "type": "timestamp with time zone",
          "primaryKey": false,
          "notNull": false,
          "default": "now()"
        },
        "preview_img": {
          "name": "preview_img",
          "type": "varchar(2048)",
          "primaryKey": false,
          "notNull": false
        },
        "sandbox_id": {
          "name": "sandbox_id",
          "type": "varchar(64)",
          "primaryKey": false,
          "notNull": false
        },
        "sandbox_url": {
          "name": "sandbox_url",
          "type": "varchar(2048)",
          "primaryKey": false,
          "notNull": false
        }
      },
      "indexes": {},
      "foreignKeys": {},
      "compositePrimaryKeys": {},
      "uniqueConstraints": {},
      "policies": {},
      "checkConstraints": {},
      "isRLSEnabled": true
    },
    "public.users": {
      "name": "users",
      "schema": "",
      "columns": {
        "id": {
          "name": "id",
          "type": "uuid",
          "primaryKey": true,
          "notNull": true
        }
      },
      "indexes": {},
      "foreignKeys": {
        "users_id_users_id_fk": {
          "name": "users_id_users_id_fk",
          "tableFrom": "users",
          "tableTo": "users",
          "schemaTo": "auth",
          "columnsFrom": [
            "id"
          ],
          "columnsTo": [
            "id"
          ],
          "onDelete": "cascade",
          "onUpdate": "cascade"
        }
      },
      "compositePrimaryKeys": {},
      "uniqueConstraints": {},
      "policies": {},
      "checkConstraints": {},
      "isRLSEnabled": true
    },
    "public.user_projects": {
      "name": "user_projects",
      "schema": "",
      "columns": {
        "user_id": {
          "name": "user_id",
          "type": "uuid",
          "primaryKey": false,
          "notNull": true
        },
        "project_id": {
          "name": "project_id",
          "type": "uuid",
          "primaryKey": false,
          "notNull": true
        },
        "created_at": {
          "name": "created_at",
          "type": "timestamp with time zone",
          "primaryKey": false,
          "notNull": false,
          "default": "now()"
        }
      },
      "indexes": {},
      "foreignKeys": {
        "user_projects_user_id_users_id_fk": {
          "name": "user_projects_user_id_users_id_fk",
          "tableFrom": "user_projects",
          "tableTo": "users",
          "columnsFrom": [
            "user_id"
          ],
          "columnsTo": [
            "id"
          ],
          "onDelete": "cascade",
          "onUpdate": "cascade"
        },
        "user_projects_project_id_projects_id_fk": {
          "name": "user_projects_project_id_projects_id_fk",
          "tableFrom": "user_projects",
          "tableTo": "projects",
          "columnsFrom": [
            "project_id"
          ],
          "columnsTo": [
            "id"
          ],
          "onDelete": "cascade",
          "onUpdate": "cascade"
        }
      },
      "compositePrimaryKeys": {
        "user_projects_user_id_project_id_pk": {
          "name": "user_projects_user_id_project_id_pk",
          "columns": [
            "user_id",
            "project_id"
          ]
        }
      },
      "uniqueConstraints": {},
      "policies": {},
      "checkConstraints": {},
      "isRLSEnabled": true
    }
  },
  "enums": {
    "public.frame_type": {
      "name": "frame_type",
      "schema": "public",
      "values": [
        "web"
      ]
    }
  },
  "schemas": {},
  "sequences": {},
  "roles": {},
  "policies": {},
  "views": {},
  "_meta": {
    "columns": {},
    "schemas": {},
    "tables": {}
  }
}